xl_factory/__init__.py
xl_factory/__main__.py
xl_factory/template/__init__.py
xl_factory/template/module/copier.yml
xl_factory/template/module/data.yaml.jinja
xl_factory/template/module/index.js.jinja
xl_factory/template/module/model.py.jinja
xl_factory/template/module/resource.py.jinja
xl_factory/template/module/views/list.vue.jinja
xl_factory/template/project/.gitignore
xl_factory/template/project/copier.yml
xl_factory/template/project/docker-compose.yaml.jinja
xl_factory/template/project/package.json.jinja
xl_factory/template/project/requirements.txt
xl_factory/template/project/tasks.py
xl_factory/template/project/uwsgi.ini.jinja
xl_factory/template/project/wsgi.py.jinja
xl_factory/template/project/backend/__init__.py.jinja
xl_factory/template/project/backend/config.py.jinja
xl_factory/template/project/backend/dockerfile
xl_factory/template/project/backend/utils/cache.py
xl_factory/template/project/backend/utils/database.py
xl_factory/template/project/backend/utils/router.py
xl_factory/template/project/backend/utils/storage.py
xl_factory/template/project/backend/utils/base/json.py
xl_factory/template/project/backend/utils/base/random.py
xl_factory/template/project/backend/utils/resource/stat.py
xl_factory/template/project/frontend/admin/App.vue
xl_factory/template/project/frontend/admin/dockerfile
xl_factory/template/project/frontend/admin/favicon.png
xl_factory/template/project/frontend/admin/index.html
xl_factory/template/project/frontend/admin/main.js
xl_factory/template/project/frontend/admin/nginx.conf.jinja
xl_factory/template/project/frontend/admin/router.js
xl_factory/template/project/frontend/admin/vite.config.js.jinja
xl_factory/template/project/frontend/public/components/SideBar.vue
xl_factory/template/project/frontend/public/components/TopBar.vue
xl_factory/template/project/frontend/public/components/xilong-ui/index.js
xl_factory/template/project/frontend/public/components/xilong-ui/button/XlAsyncButton.vue
xl_factory-0.5.1.dist-info/METADATA
xl_factory-0.5.1.dist-info/WHEEL
xl_factory-0.5.1.dist-info/RECORD
