Metadata-Version: 2.1
Name: xl-factory
Version: 0.5.1
Summary: xilong factory library
Project-URL: Homepage, https://git.xilonglab.com/xilong/xl-factory
Project-URL: Bug Tracker, https://git.xilonglab.com/xilong/xl-factory/issues
Author-email: xilong <xilonglab@163.com>
Classifier: License :: OSI Approved :: MIT License
Classifier: Operating System :: OS Independent
Classifier: Programming Language :: Python :: 3
Requires-Python: >=3.7
Requires-Dist: copier==8.1.0
Requires-Dist: sqlalchemy==1.4.39
